{"G2t8KDM79DYF8wPkjVSVng==":"johnathan___an_bacus_beag__%E2%80%A2_instagram_photos_and_videos%202-600x594.jpg","03EiOL0zjnXew4+zr2A1kA==":"johnathan___an_bacus_beag__%E2%80%A2_instagram_photos_and_videos%203-596x595.jpg","EtSlq23/E5RO8xLIMz3ScA==":"johnathan___an_bacus_beag__%E2%80%A2_instagram_photos_and_videos%204-599x594.jpg","+eEe5I9hGz7Q5nltXTGwaQ==":"johnathan___an_bacus_beag__%E2%80%A2_instagram_photos_and_videos%205-599x595.jpg","Rz7KvIp8ERQV3OaofgCpDQ==":"johnathan___an_bacus_beag__%E2%80%A2_instagram_photos_and_videos%206-598x592.jpg","xcJPODHl7+Kl/QzU/lCwWQ==":"johnathan___an_bacus_beag__%E2%80%A2_instagram_photos_and_videos%207-596x595.jpg","wBEvdypfKikGCtd9JOPgzA==":"johnathan___an_bacus_beag__%E2%80%A2_instagram_photos_and_videos%208-598x594.jpg","FwrW16Ed5LchYz427ALNGA==":"johnathan___an_bacus_beag__%E2%80%A2_instagram_photos_and_videos-599x601.jpg","Ayb8KprEgjZtxNp7dW4r7Q==":"johnathan___an_bacus_beag__%E2%80%A2_instagram_photos_and_videos%209-600x594.jpg","BddrdzP1TjG/N5vexcSu4g==":"_5__deborah_hunt-529x526.jpg","uwEwy6mG2SHShOblGSbSJQ==":"shop_name-529x70.png"}